pytvm/__init__.py
pytvm/utils.py
pytvm/engine/__init__.py
pytvm/engine/engine.py
pytvm/engine/engine_c.py
pytvm/engine/libemulator-mac-arm64.dylib
pytvm/engine/__pycache__/__init__.cpython-311.pyc
pytvm/engine/__pycache__/engine.cpython-311.pyc
pytvm/engine/__pycache__/engine_c.cpython-311.pyc
pytvm/transaction_emulator/__init__.py
pytvm/transaction_emulator/blockchain_api.py
pytvm/transaction_emulator/trace.py
pytvm/transaction_emulator/transaction_emulator.py
pytvm/tvm_emulator/__init__.py
pytvm/tvm_emulator/tvm_emulator.py
pytvm-0.0.15.dist-info/METADATA
pytvm-0.0.15.dist-info/WHEEL
pytvm-0.0.15.dist-info/top_level.txt
pytvm-0.0.15.dist-info/RECORD
