Metadata-Version: 2.2
Name: pytvm
Version: 0.0.15
Summary: Python TVM emulator
Home-page: https://github.com/yungwine/pytvm
Author: Maksim Kurbatov
Author-email: cyrbatoff@gmail.com
Classifier: Programming Language :: Python :: 3.9
Classifier: Programming Language :: Python :: 3.10
Classifier: Programming Language :: Python :: 3.11
Classifier: Topic :: Software Development :: Libraries
Requires-Python: >=3.9
Requires-Dist: pytoniq-core>=0.1.31
Dynamic: author
Dynamic: author-email
Dynamic: classifier
Dynamic: description
Dynamic: description-content-type
Dynamic: home-page
Dynamic: requires-dist
Dynamic: requires-python
Dynamic: summary
